{
  "skill": "global-knowledge",
  "inheritance": "master-only",
  "connections": [
    {
      "target": ".github/skills/knowledge-synthesis/SKILL.md",
      "type": "stores",
      "strength": 0.75,
      "reason": "Synthesis outputs go to global KB"
    },
    {
      "target": ".github/skills/meditation-facilitation/SKILL.md",
      "type": "informs",
      "strength": 0.65,
      "reason": "Meditation creates global insights"
    },
    {
      "target": ".github/skills/bootstrap-learning/SKILL.md",
      "type": "accelerates",
      "strength": 0.8,
      "reason": "Prior knowledge speeds learning"
    }
  ],
  "triggers": [
    "knowledge",
    "insight",
    "pattern",
    "cross-project",
    "global",
    "reusable"
  ]
}
